setup.cfg
setup.py
code_crypt/__init__.py
code_crypt/cli.py
code_crypt/core.py
code_crypt/defaults.py
code_crypt/errors.py
code_crypt/metadata.py
code_crypt.egg-info/PKG-INFO
code_crypt.egg-info/SOURCES.txt
code_crypt.egg-info/dependency_links.txt
code_crypt.egg-info/entry_points.txt
code_crypt.egg-info/requires.txt
code_crypt.egg-info/top_level.txt