Metadata-Version: 1.1
Name: code-crypt
Version: 0.0.10
Summary: Code Crypt
Home-page: https://github.com/Nextdoor/code-crypt
Author: Nextdoor Engineering
Author-email: nehal@nextdoor.com
License: Apache License, Version 2.0
Download-URL: https://github.com/Nextdoor/code-crypt/tarball/v0.0.10
Platform: UNKNOWN
